README.md
setup.py
shirow/__init__.py
shirow/ioloop.py
shirow/request.py
shirow/server.py
shirow/util.py
shirow.egg-info/PKG-INFO
shirow.egg-info/SOURCES.txt
shirow.egg-info/dependency_links.txt
shirow.egg-info/requires.txt
shirow.egg-info/top_level.txt