Metadata-Version: 1.0
Name: shirow
Version: 0.3
Summary: Shirow package
Home-page: https://github.com/tolstoyevsky/shirow
Author: Evgeny Golyshev
Author-email: Evgeny Golyshev <eugulixes@gmail.com>
License: http://www.apache.org/licenses/LICENSE-2.0
Platform: UNKNOWN
